Metadata-Version: 2.1
Name: NifflerAnalyticsSDK
Version: 1.0.4
Summary: This is the official Python SDK for Niffler Analytics.
Home-page: https://code.yidianshihui.com/j.a.r.v.i.s/niffer-python
Author: ShiKun
Author-email: 429143597@qq.com
License: UNKNOWN
Platform: UNKNOWN
